snowbank/__init__.py
snowbank-0.1.dist-info/LICENSE
snowbank-0.1.dist-info/METADATA
snowbank-0.1.dist-info/WHEEL
snowbank-0.1.dist-info/top_level.txt
snowbank-0.1.dist-info/RECORD
